LICENSE
MANIFEST.in
README.md
requirements.txt
setup.py
calibrate_receiver.egg-info/PKG-INFO
calibrate_receiver.egg-info/SOURCES.txt
calibrate_receiver.egg-info/dependency_links.txt
calibrate_receiver.egg-info/entry_points.txt
calibrate_receiver.egg-info/requires.txt
calibrate_receiver.egg-info/top_level.txt
config/__init__.py
config/config_MS2830A.json
config/config_MS2830A.json.backup
config/config_interface.json
src/Anritsu_MS2830A.py
src/Utils.py
src/__init__.py
src/azure.tcl
src/gui.py
src/gui_support.py
src/main.py
src/pyvisa_commands.py
src/tabs/__init__.py
src/tabs/configuration_tab.py
src/tabs/connect_tab.py
src/tabs/measure_tab.py
theme/dark.tcl
theme/light.tcl
theme/dark/box-accent.png
theme/dark/box-basic.png
theme/dark/box-hover.png
theme/dark/box-invalid.png
theme/dark/button-hover.png
theme/dark/card.png
theme/dark/check-accent.png
theme/dark/check-basic.png
theme/dark/check-hover.png
theme/dark/check-tri-accent.png
theme/dark/check-tri-basic.png
theme/dark/check-tri-hover.png
theme/dark/circle-accent.png
theme/dark/circle-basic.png
theme/dark/circle-hover.png
theme/dark/combo-button-basic.png
theme/dark/combo-button-focus.png
theme/dark/combo-button-hover.png
theme/dark/down-accent.png
theme/dark/down.png
theme/dark/empty.png
theme/dark/hor-accent.png
theme/dark/hor-basic.png
theme/dark/hor-hover.png
theme/dark/notebook.png
theme/dark/off-basic.png
theme/dark/on-accent.png
theme/dark/on-basic.png
theme/dark/outline-basic.png
theme/dark/outline-hover.png
theme/dark/radio-accent.png
theme/dark/radio-basic.png
theme/dark/radio-hover.png
theme/dark/radio-tri-accent.png
theme/dark/radio-tri-basic.png
theme/dark/radio-tri-hover.png
theme/dark/rect-accent-hover.png
theme/dark/rect-accent.png
theme/dark/rect-basic.png
theme/dark/rect-hover.png
theme/dark/right.png
theme/dark/scale-hor.png
theme/dark/scale-vert.png
theme/dark/separator.png
theme/dark/size.png
theme/dark/tab-basic.png
theme/dark/tab-disabled.png
theme/dark/tab-hover.png
theme/dark/tick-hor-accent.png
theme/dark/tick-hor-basic.png
theme/dark/tick-hor-hover.png
theme/dark/tick-vert-accent.png
theme/dark/tick-vert-basic.png
theme/dark/tick-vert-hover.png
theme/dark/tree-basic.png
theme/dark/tree-pressed.png
theme/dark/up-accent.png
