Metadata-Version: 2.1
Name: calibrate-receiver
Version: 0.8.0
Summary: A graphic tool used to calibrate a multifeed receiver
Home-page: https://github.com/LorenzoMonti/calibrate-multifeed-receiver
Author: Lorenzo Monti
Author-email: lorenzo.monti@inaf.it
License: MIT
Platform: all
Classifier: Programming Language :: Python :: 3.8
Classifier: Operating System :: Microsoft :: Windows
Classifier: Operating System :: POSIX :: Linux
Classifier: License :: OSI Approved :: MIT License
